adversarial_attacks/__init__.py
adversarial_attacks/fgsm.py
adversarial_attacks-0.1.dist-info/METADATA
adversarial_attacks-0.1.dist-info/WHEEL
adversarial_attacks-0.1.dist-info/top_level.txt
adversarial_attacks-0.1.dist-info/RECORD
